grgr/__init__.py
grgr/dev/__init__.py
grgr/dev/typing.py
grgr/ggplot2/__init__.py
grgr/ggplot2/basic.py
grgr/ggplot2/facet.py
grgr/ggplot2/layer.py
grgr/ggplot2/scale.py
grgr/ggplot2/theme.py
grgr-0.1.0.dist-info/WHEEL
grgr-0.1.0.dist-info/METADATA
grgr-0.1.0.dist-info/RECORD
