Metadata-Version: 2.1
Name: grgr
Version: 0.1.0
Summary: `grgr` is a wrapper library for using `ggplot2` from `python`.
Home-page: https://github.com/7cm-diameter/grgr/wiki
License: MIT
Author: 7cm-diameter
Author-email: from.this.ridiculous.loop@gmail.com
Requires-Python: >=3.7.1,<3.11
Classifier: License :: OSI Approved :: MIT License
Classifier: Programming Language :: Python :: 3
Classifier: Programming Language :: Python :: 3.8
Classifier: Programming Language :: Python :: 3.9
Requires-Dist: numpy (>=1.21.2,<2.0.0)
Requires-Dist: pandas (>=1.3.2,<2.0.0)
Requires-Dist: rpy2 (>=3.4.5,<4.0.0)
Project-URL: Repository, https://github.com/7cm-diameter/grgr
